satoristore/__init__.py
satoristore/memory_bank.py
satoristore/memory_bank_factory.py
satoristore/model_manager.py
satoristore/multimodal_memory_bank.py
satoristore/text_memory_bank.py
satoristore-0.1.6.dist-info/LICENSE
satoristore-0.1.6.dist-info/METADATA
satoristore-0.1.6.dist-info/WHEEL
satoristore-0.1.6.dist-info/entry_points.txt
satoristore-0.1.6.dist-info/RECORD
