Metadata-Version: 2.1
Name: satoristore
Version: 0.1.6
Summary: A memory architecture for AI agents supporting hierarchical and multimodal data.
License: MIT
Author: Kentauros AI
Author-email: partners@kentauros.ai
Requires-Python: >=3.10,<4.0
Classifier: License :: OSI Approved :: MIT License
Classifier: Programming Language :: Python :: 3
Classifier: Programming Language :: Python :: 3.10
Classifier: Programming Language :: Python :: 3.11
Classifier: Programming Language :: Python :: 3.12
Classifier: Programming Language :: Python :: 3.13
Requires-Dist: Pillow (>=10.0.0,<11.0.0)
Requires-Dist: PyYAML (>=6.0.1,<7.0.0)
Requires-Dist: SQLAlchemy (>=2.0.25,<3.0.0)
Requires-Dist: clip-anytorch (>=2.5.0,<3.0.0)
Requires-Dist: numpy (>=1.24.6,<2.0.0)
Requires-Dist: pydantic (>=2.9.2,<3.0.0)
Requires-Dist: qdrant-client (>=1.8.0,<2.0.0)
Requires-Dist: sentence-transformers (>=3.1.1,<4.0.0)
Requires-Dist: torch (==2.2.2)
Requires-Dist: torchvision (==0.17.2)
